README.md
setup.cfg
setup.py
fibo_sum/__init__.py
fibo_sum/fibo_sum.py
fibo_sum.egg-info/PKG-INFO
fibo_sum.egg-info/SOURCES.txt
fibo_sum.egg-info/dependency_links.txt
fibo_sum.egg-info/top_level.txt